sudoku/__init__.py
sussudoku-0.2.dist-info/METADATA
sussudoku-0.2.dist-info/WHEEL
sussudoku-0.2.dist-info/top_level.txt
sussudoku-0.2.dist-info/RECORD
