Metadata-Version: 2.1
Name: sussudoku
Version: 0.2
Summary: Solve Sudoku with Python.
Home-page: https://gitlab.com/MHenderson1/sudoku
Author: Matthew Henderson
Author-email: matthew.james.henderson@gmail.com
License: MIT
Platform: UNKNOWN
